{
  "title": "ASSIGNMENTS",
  "outline": [
    {
      "level": "H1",
      "text": "This sample student paper is a business report task which demonstrates the requirements for APA (7th edition) referencing style.",
      "page": 1
    },
    {
      "level": "H1",
      "text": "The guidelines and comments have been colour-coded:",
      "page": 1
    },
    {
      "level": "H1",
      "text": "Formatting requirements - blue",
      "page": 1
    },
    {
      "level": "H1",
      "text": "Academic writing and addressing the task - red",
      "page": 1
    },
    {
      "level": "H1",
      "text": "Referencing guidelines - yellow",
      "page": 1
    }
  ]
}